ecabc/__init__.py
ecabc/abc.py
ecabc/bee.py
ecabc/parameter.py
ecabc/utils.py
examples/minimize_integers.py
tests/test_all.py
ecabc-3.0.1.dist-info/LICENSE
ecabc-3.0.1.dist-info/METADATA
ecabc-3.0.1.dist-info/WHEEL
ecabc-3.0.1.dist-info/top_level.txt
ecabc-3.0.1.dist-info/RECORD
