Metadata-Version: 2.1
Name: ecabc
Version: 3.0.1
Summary: Artificial bee colony for function parameter optimization
Author-email: Sanskriti Sharma <Sanskriti_Sharma@student.uml.edu>, Hernan Gelaf-Romer <Hernan_Gelafromer@student.uml.edu>, Travis Kessler <travis.j.kessler@gmail.com>
Project-URL: Homepage, https://github.com/ecrl/ecabc
Project-URL: Bug Tracker, https://github.com/ecrl/ecabc/issues
Classifier: Programming Language :: Python :: 3.11
Classifier: License :: OSI Approved :: MIT License
Classifier: Operating System :: OS Independent
Requires-Python: >=3.11
License-File: LICENSE
